napari_manual_registration/__init__.py
napari_manual_registration/_widget.py
napari_manual_registration/napari.yaml
napari_manual_registration/_tests/__init__.py
napari_manual_registration-0.0.4.dist-info/licenses/LICENSE
napari_manual_registration-0.0.4.dist-info/METADATA
napari_manual_registration-0.0.4.dist-info/WHEEL
napari_manual_registration-0.0.4.dist-info/entry_points.txt
napari_manual_registration-0.0.4.dist-info/top_level.txt
napari_manual_registration-0.0.4.dist-info/RECORD
