Metadata-Version: 2.4
Name: napari-manual-registration
Version: 0.0.4
Summary: A simple plugin to register 2 views of the same object
Home-page: https://github.com/jules-vanaret/napari-manual-registration
Author: Alice Gros, Jules Vanaret
Author-email: jules.vanaret@univ-amu.fr
License: BSD-3-Clause
Project-URL: Bug Tracker, https://github.com/jules-vanaret/napari-manual-registration/issues
Project-URL: Documentation, https://github.com/jules-vanaret/napari-manual-registration#README.md
Project-URL: Source Code, https://github.com/jules-vanaret/napari-manual-registration
Project-URL: User Support, https://github.com/jules-vanaret/napari-manual-registration/issues
Classifier: Development Status :: 2 - Pre-Alpha
Classifier: Framework :: napari
Classifier: Intended Audience :: Developers
Classifier: License :: OSI Approved :: BSD License
Classifier: Operating System :: OS Independent
Classifier: Programming Language :: Python
Classifier: Programming Language :: Python :: 3
Classifier: Programming Language :: Python :: 3 :: Only
Classifier: Programming Language :: Python :: 3.8
Classifier: Programming Language :: Python :: 3.9
Classifier: Programming Language :: Python :: 3.10
Classifier: Topic :: Scientific/Engineering :: Image Processing
Requires-Python: >=3.8
License-File: LICENSE
Requires-Dist: numpy
Requires-Dist: scipy
Requires-Dist: magicgui
Requires-Dist: qtpy
Requires-Dist: pyclesperanto_prototype
Requires-Dist: scikit-image
Provides-Extra: testing
Requires-Dist: tox; extra == "testing"
Requires-Dist: pytest; extra == "testing"
Requires-Dist: pytest-cov; extra == "testing"
Requires-Dist: pytest-qt; extra == "testing"
Requires-Dist: napari; extra == "testing"
Requires-Dist: pyqt5; extra == "testing"
Dynamic: license-file
